liteauto/__init__.py
liteauto/agents/__init__.py
liteauto/agents/hf_coder.py
liteauto/agents/smolagent_coder.py
liteauto/ai_web_search/__init__.py
liteauto/ai_web_search/ai_enhanced_search.py
liteauto/arxivlite/__init__.py
liteauto/arxivlite/analysis.py
liteauto/arxivlite/arxiv_playwright.py
liteauto/arxivlite/const.py
liteauto/arxivlite/final.py
liteauto/arxivlite/main.py
liteauto/arxivlite/schema.py
liteauto/arxivlite/utils.py
liteauto/deep_research/__init__.py
liteauto/deep_research/deep_research.py
liteauto/deep_research/deep_research_email.py
liteauto/deep_research/main.py
liteauto/evallite/.deepeval-cache.json
liteauto/evallite/.deepeval_telemtry.txt
liteauto/evallite/README.md
liteauto/evallite/__init__.py
liteauto/evallite/main.py
liteauto/gmaillite/__init__.py
liteauto/gmaillite/_gmail_auto.py
liteauto/misc/__init__.py
liteauto/misc/claude_streamlit_app.py
liteauto/parselite/__init__.py
liteauto/parselite/_main.py
liteauto/project_to_prompt/__init__.py
liteauto/project_to_prompt/_proj_to_prompt.py
liteauto/project_to_prompt/project_to_markdown.py
liteauto/promptlite/__init__.py
liteauto/promptlite/claude/CLAUDE_SYS_PROMPT.md
liteauto/promptlite/claude/PREVIEW_SYS_PROMPT.md
liteauto/promptlite/claude/__init__.py
liteauto/promptlite/code/CODE_EXPLANATION_CLAUDE_PROMPT.md
liteauto/promptlite/code/CODE_GENERATION_PROMPT.md
liteauto/promptlite/code/__init__.py
liteauto/promptlite/content_writer/EXPERT_TECHNICAL_WRITER.md
liteauto/promptlite/content_writer/__init__.py
liteauto/promptlite/education/TECHNICAL_EXPLANATIONS.md
liteauto/promptlite/education/__init__.py
liteauto/promptlite/language/PYTHON_CODER_PROMPT.md
liteauto/promptlite/language/__init__.py
liteauto/promptlite/main.py
liteauto/promptlite/personas/AI_TECH_LEAD_PROMPT.md
liteauto/promptlite/personas/BRAINSTROM_BUDDY_PROMPT.md
liteauto/promptlite/personas/__init__.py
liteauto/promptlite/reasoning/PREDICTIVE_QUESTION_REASONING_PROMPT.md
liteauto/promptlite/reasoning/__init__.py
liteauto-0.2.25.dist-info/METADATA
liteauto-0.2.25.dist-info/WHEEL
liteauto-0.2.25.dist-info/entry_points.txt
liteauto-0.2.25.dist-info/RECORD
