Metadata-Version: 2.3
Name: liteauto
Version: 0.2.25
Summary: free google results
License: MIT
Author: Kammari Santhosh
Requires-Python: >=3.10,<4.0
Classifier: License :: OSI Approved :: MIT License
Classifier: Programming Language :: Python :: 3
Classifier: Programming Language :: Python :: 3.10
Classifier: Programming Language :: Python :: 3.11
Classifier: Programming Language :: Python :: 3.12
Classifier: Programming Language :: Python :: 3.13
Requires-Dist: certifi (>=2024.12.14,<2025.0.0)
Requires-Dist: duckduckgo-search (>=7.3.2,<8.0.0)
Requires-Dist: git-python (==1.0.3)
Requires-Dist: googlesearch-python (>=1.3.0,<2.0.0)
Requires-Dist: langchain_openai (==0.3.4)
Requires-Dist: litegen (>=0.0.98,<0.0.99)
Requires-Dist: liteutils (>=0.0.30,<0.0.31)
Requires-Dist: md2pdf (>=1.0.1,<2.0.0)
Requires-Dist: nltk (>=3.9.1,<4.0.0)
Requires-Dist: pandas (==2.2.3)
Requires-Dist: pyautogui (>=0.9.54,<0.10.0)
Requires-Dist: pypdf2 (==3.0.1)
Requires-Dist: trafilatura (==2.0.0)
Requires-Dist: wikipedia (>=1.4.0,<2.0.0)
Requires-Dist: wordllama (==0.3.9)
Requires-Dist: youtube-transcript-api (==0.6.3)
Project-URL: Repository, https://github.com/santhosh/
